{"code":"3021760400043","name":"Pomme Banane 90 g","brands":[ "materne", "pom-potes" ],"allergens":[ ],"categories":[ "en:plant-based-foods-and-beverages", "en:plant-based-foods", "en:desserts", "en:fruits-and-vegetables-based-foods", "en:fruits-based-foods", "en:compotes", "en:apple-compotes", "en:compotes-to-drink", "en:light-compotes", "fr:compotes-pommes-banane" ],"ingredients":[{"text":"Pomme","percent":"77.9"},{"text":"banane","percent":"20.4"},{"text":"sucre","percent":"1.13333333333333"},{"text":"jus de citron concentré si nécessaire pour réguler l'acidité","percent":"0.283333333333331"},{"text":"antioxydant","percent":"0.283333333333331"},{"text":"acide ascorbique","percent":"0.283333333333331"}]}